AUTHORS.rst
CONTRIBUTING.rst
HISTORY.rst
LICENSE
MANIFEST.in
README.rst
setup.py
tweetrssfeed/__init__.py
tweetrssfeed/tweetrssfeed.py
tweetrssfeed.egg-info/PKG-INFO
tweetrssfeed.egg-info/SOURCES.txt
tweetrssfeed.egg-info/dependency_links.txt
tweetrssfeed.egg-info/entry_points.txt
tweetrssfeed.egg-info/not-zip-safe
tweetrssfeed.egg-info/requires.txt
tweetrssfeed.egg-info/top_level.txt