Metadata-Version: 1.1
Name: tweetrssfeed
Version: 0.1.6
Summary: Tweet RSS Feeds
Home-page: https://github.com/gam-phon/tweetrssfeed
Author: Yaser Alraddadi
Author-email: yaser@yr.sa
License: BSD
Keywords: tweetrssfeed twitter rss
Platform: UNKNOWN
Classifier: Development Status :: 2 - Pre-Alpha
Classifier: Intended Audience :: Developers
Classifier: License :: OSI Approved :: BSD License
Classifier: Natural Language :: English
Classifier: Programming Language :: Python :: 2
Classifier: Programming Language :: Python :: 2.6
Classifier: Programming Language :: Python :: 2.7
Classifier: Programming Language :: Python :: 3
Classifier: Programming Language :: Python :: 3.3
